cmmap.py
setup.py
cmmap.egg-info/PKG-INFO
cmmap.egg-info/SOURCES.txt
cmmap.egg-info/dependency_links.txt
cmmap.egg-info/requires.txt
cmmap.egg-info/top_level.txt