Metadata-Version: 1.0
Name: cmmap
Version: 0.0.1
Summary: mmap cffi wrapper
Home-page: https://github.com/michelp/pyczmq
Author: Michel Pelletier
Author-email: pelletier.michel@yahoo.com
License: BSD
Platform: UNKNOWN
